yet_more_functools/VERSION
yet_more_functools/__init__.py
yet_more_functools/sow_reap/__init__.py
yet_more_functools/sow_reap/sow_reap.py
yet_more_functools/stash_grab/__init__.py
yet_more_functools/stash_grab/stash_grab.py
yet_more_functools/throw_catch/__init__.py
yet_more_functools/throw_catch/thow_catch.py
yet_more_functools/util/__init__.py
yet_more_functools/util/util.py
yet_more_functools-2.0.0.dist-info/licenses/LICENSE.txt
yet_more_functools-2.0.0.dist-info/METADATA
yet_more_functools-2.0.0.dist-info/WHEEL
yet_more_functools-2.0.0.dist-info/top_level.txt
yet_more_functools-2.0.0.dist-info/RECORD
