Metadata-Version: 2.4
Name: yet_more_functools
Version: 2.0.0
Summary: Additional functional tools for python.
License-Expression: MIT
Project-URL: Homepage, https://gitlab.com/roger_wilson/yetmorefunctools
Project-URL: Documentation, https://gitlab.com/roger_wilson/yetmorefunctools/-/blob/2.0.0-docs/README.md
Project-URL: Repository, https://gitlab.com/roger_wilson/yetmorefunctools.git
Project-URL: Issues, https://gitlab.com/roger_wilson/yetmorefunctools/-/issues
Project-URL: Changelog, https://gitlab.com/roger_wilson/yetmorefunctools/-/blob/2.0.0-docs/RELEASE_NOTES.md
Keywords: functional
Requires-Python: >=3.11
License-File: LICENSE.txt
Dynamic: license-file
